sklearn_transformer_extensions/__init__.py
sklearn_transformer_extensions/compose/__init__.py
sklearn_transformer_extensions/compose/_column_transformer.py
sklearn_transformer_extensions/compose/tests/__init__.py
sklearn_transformer_extensions/compose/tests/test_column_transformer.py
sklearn_transformer_extensions/metrics/__init__.py
sklearn_transformer_extensions/metrics/_scorer.py
sklearn_transformer_extensions/pipeline.py
sklearn_transformer_extensions/preprocessing/__init__.py
sklearn_transformer_extensions/preprocessing/_function_transformer.py
sklearn_transformer_extensions/preprocessing/tests/__init__.py
sklearn_transformer_extensions/preprocessing/tests/test_function_transformer.py
sklearn_transformer_extensions/tests/__init__.py
sklearn_transformer_extensions/tests/test_base.py
sklearn_transformer_extensions/tests/test_pipeline.py
sklearn_transformer_extensions/xyadapter.py
sklearn_transformer_extensions/xydata.py
sklearn_transformer_extensions-0.2.3.dist-info/LICENSE
sklearn_transformer_extensions-0.2.3.dist-info/WHEEL
sklearn_transformer_extensions-0.2.3.dist-info/METADATA
sklearn_transformer_extensions-0.2.3.dist-info/RECORD
